sandtank_ml/__init__.py
sandtank_ml/app/__init__.py
sandtank_ml/app/jupyter.py
sandtank_ml/app/main.py
sandtank_ml/app/engine/__init__.py
sandtank_ml/app/engine/ai/__init__.py
sandtank_ml/app/engine/ai/ml.py
sandtank_ml/app/engine/ai/run.py
sandtank_ml/app/engine/ai/refs/Init_press.pfb
sandtank_ml/app/engine/ai/refs/perm.pfb
sandtank_ml/app/engine/parflow/__init__.py
sandtank_ml/app/engine/parflow/run.py
sandtank_ml/app/engine/parflow/refs/Init_press.pfb
sandtank_ml/app/engine/parflow/refs/SandTank.pfsol
sandtank_ml/app/engine/parflow/refs/SandTank_Indicator.pfb
sandtank_ml/app/engine/parflow/refs/__init__.py
sandtank_ml/app/engine/parflow/refs/perm.pfb
sandtank_ml/app/engine/parflow/refs/run.yaml
sandtank_ml/app/engine/parflow/refs/__pycache__/__init__.cpython-39.pyc
sandtank_ml/app/engine/xai/__init__.py
sandtank_ml/app/engine/xai/run.py
sandtank_ml/app/ui/__init__.py
sandtank_ml/app/ui/ai.py
sandtank_ml/app/ui/parflow.py
sandtank_ml/app/ui/xai.py
trame_sandtank_ml-1.0.0.dist-info/LICENSE
trame_sandtank_ml-1.0.0.dist-info/METADATA
trame_sandtank_ml-1.0.0.dist-info/WHEEL
trame_sandtank_ml-1.0.0.dist-info/entry_points.txt
trame_sandtank_ml-1.0.0.dist-info/top_level.txt
trame_sandtank_ml-1.0.0.dist-info/RECORD
