Metadata-Version: 2.1
Name: trame-sandtank-ml
Version: 1.0.0
Summary: Interactive application blending ParFlow execution and AI models for validation
Author: Kitware Inc.
License: BSD License
Keywords: Python,Interactive,Web,Application,Framework
Classifier: Development Status :: 1 - Planning
Classifier: Environment :: Web Environment
Classifier: License :: OSI Approved :: BSD License
Classifier: Natural Language :: English
Classifier: Operating System :: OS Independent
Classifier: Programming Language :: Python :: 3 :: Only
Classifier: Programming Language :: JavaScript
Classifier: Topic :: Software Development :: Libraries :: Application Frameworks
Classifier: Topic :: Software Development :: Libraries :: Python Modules
License-File: LICENSE
Requires-Dist: trame (>=2.0.0rc2)
Requires-Dist: pftools[io] (>=1.3.2)
Requires-Dist: pytorch-lightning
Requires-Dist: xaitk-saliency
